pipeline/README.md
pipeline/SOLUTIONS.md
pipeline/__init__.py
pipeline/four_stage_pipeline.py
pipeline/orchestrator.py
pipeline/yaml_runner.py
pipeline/converters/__init__.py
pipeline/converters/factory.py
pipeline/converters/jsonl_converter.py
pipeline/converters/yaml_converter.py
pipeline/deduplication/deduplicator.py
pipeline/distill/__init__.py
pipeline/distill/quality_rules.py
pipeline/distill/quality_validator.py
pipeline/notifications/__init__.py
pipeline/notifications/discord_notifier.py
pipeline/ocr/__init__.py
pipeline/ocr/paddle_to_yaml.py
pipeline/parsers/__init__.py
pipeline/parsers/base.py
pipeline/parsers/chunk_parser.py
pipeline/parsers/config_schema.py
pipeline/parsers/cpu_pdf_parser.py
pipeline/parsers/docling_yaml_adapter.py
pipeline/parsers/factory.py
pipeline/parsers/hwp_parser.py
pipeline/parsers/hwp_yaml_adapter.py
pipeline/parsers/hwpx_yaml_adapter.py
pipeline/parsers/safe_parser.py
pipeline/parsers/special_clause_parser.py
pipeline/parsers/unified_parser.py
pipeline/qa/__init__.py
pipeline/qa/config.py
pipeline/qa/merge_engine.py
pipeline/qa/qa_pipeline.py
pipeline/qa/qa_prompt.py
pipeline/qa/scope_guard.py
pipeline/qa/scope_validator.py
pipeline/quality/__init__.py
pipeline/quality/auto_validator.py
pipeline/quality/autofix.py
pipeline/quality/ocr_remap.py
pipeline/quality/table_quality.py
pipeline/rag/__init__.py
pipeline/rag/chunk_builder.py
pipeline/rag/context_assembler.py
pipeline/rag/distillation.py
pipeline/rag/doc_classifier.py
pipeline/rag/faiss_indexer.py
pipeline/rag/prompt_templates.py
pipeline/rag/query_classifier.py
pipeline/rag/retriever.py
pipeline/security/__init__.py
pipeline/security/hwp_encryption.py
pipeline/triage/__init__.py
pipeline/triage/pdf_classifier.py
pipeline/utils/__init__.py
pipeline/utils/timeout_calculator.py
pdf_yaml_pipeline-0.1.0.dist-info/METADATA
pdf_yaml_pipeline-0.1.0.dist-info/WHEEL
pdf_yaml_pipeline-0.1.0.dist-info/entry_points.txt
pdf_yaml_pipeline-0.1.0.dist-info/licenses/LICENSE
pdf_yaml_pipeline-0.1.0.dist-info/RECORD
