Metadata-Version: 2.4
Name: pdf-yaml-pipeline
Version: 0.1.0
Summary: GPU-accelerated document processing: PDF/HWP → YAML for LLM training data
Project-URL: Homepage, https://github.com/seunghyuoffice-design/pdf-yaml-pipeline
Project-URL: Documentation, https://github.com/seunghyuoffice-design/pdf-yaml-pipeline#readme
Project-URL: Repository, https://github.com/seunghyuoffice-design/pdf-yaml-pipeline.git
Project-URL: Issues, https://github.com/seunghyuoffice-design/pdf-yaml-pipeline/issues
Author-email: Dyarchy Team <dyarchy@example.com>
License-Expression: MIT
License-File: LICENSE
Keywords: docling,document,hwp,korean,llm,parser,pdf,training-data,yaml
Classifier: Development Status :: 4 - Beta
Classifier: Intended Audience :: Developers
Classifier: Intended Audience :: Science/Research
Classifier: License :: OSI Approved :: MIT License
Classifier: Operating System :: OS Independent
Classifier: Programming Language :: Python :: 3
Classifier: Programming Language :: Python :: 3.10
Classifier: Programming Language :: Python :: 3.11
Classifier: Programming Language :: Python :: 3.12
Classifier: Topic :: Scientific/Engineering :: Artificial Intelligence
Classifier: Topic :: Text Processing :: General
Requires-Python: >=3.10
Requires-Dist: loguru>=0.7
Requires-Dist: pillow>=10.0
Requires-Dist: pydantic>=2.0
Requires-Dist: pyyaml>=6.0
Requires-Dist: tqdm>=4.60
Provides-Extra: dev
Requires-Dist: mypy>=1.0; extra == 'dev'
Requires-Dist: pytest-cov>=4.0; extra == 'dev'
Requires-Dist: pytest>=7.0; extra == 'dev'
Requires-Dist: ruff>=0.1.0; extra == 'dev'
Provides-Extra: full
Requires-Dist: docling-core>=2.50; extra == 'full'
Requires-Dist: docling>=2.50; extra == 'full'
Requires-Dist: hwp2yaml>=0.6; extra == 'full'
Requires-Dist: olefile>=0.46; extra == 'full'
Requires-Dist: redis>=5.0; extra == 'full'
Requires-Dist: torch>=2.0; extra == 'full'
Requires-Dist: torchvision>=0.15; extra == 'full'
Provides-Extra: gpu
Requires-Dist: torch>=2.0; extra == 'gpu'
Requires-Dist: torchvision>=0.15; extra == 'gpu'
Provides-Extra: hwp
Requires-Dist: hwp2yaml>=0.6; extra == 'hwp'
Requires-Dist: olefile>=0.46; extra == 'hwp'
Provides-Extra: pdf
Requires-Dist: docling-core>=2.50; extra == 'pdf'
Requires-Dist: docling>=2.50; extra == 'pdf'
Provides-Extra: queue
Requires-Dist: redis>=5.0; extra == 'queue'
